sqrl_python_interface/agents/base_agent.py
sqrl_python_interface/utils/python_connection.py
sqrl_python_interface/utils/structures/ball_prediction_struct.py
sqrl_python_interface/utils/structures/game_data_struct.py
sqrl_python_interface-0.2.0.dist-info/METADATA
sqrl_python_interface-0.2.0.dist-info/WHEEL
sqrl_python_interface-0.2.0.dist-info/top_level.txt
sqrl_python_interface-0.2.0.dist-info/RECORD
